autothalix/__init__.py
autothalix/logging.py
autothalix/measurements.py
autothalix/utils.py
tests/__init__.py
tests/test_ca.py
tests/test_cv.py
tests/test_eis.py
tests/test_imp.py
tests/test_lsv.py
tests/test_ocp.py
AutoThaliX-0.3.1.dist-info/LICENSE
AutoThaliX-0.3.1.dist-info/METADATA
AutoThaliX-0.3.1.dist-info/WHEEL
AutoThaliX-0.3.1.dist-info/top_level.txt
AutoThaliX-0.3.1.dist-info/RECORD
