Metadata-Version: 2.1
Name: AutoThaliX
Version: 0.3.1
Summary: A set of tools to work with tales potentiostats. Uses tales_remote
Home-page: https://github.com/Arkady-A/autothalix
Author: ArkadyA
Author-email: arkadymirz@gmail.com
License: UNKNOWN
Platform: UNKNOWN
Classifier: Programming Language :: Python :: 3
Classifier: License :: OSI Approved :: MIT License
Classifier: Operating System :: OS Independent
Requires-Python: >=3.9
License-File: LICENSE
Requires-Dist: PyYAML ==6.0
Requires-Dist: thales-remote ==1.0.1
Requires-Dist: zahner-analysis ==1.1.0
